switchgen/__init__.py
switchgen/__main__.py
switchgen/app.py
switchgen/core/__init__.py
switchgen/core/comfy_init.py
switchgen/core/config.py
switchgen/core/downloader.py
switchgen/core/engine.py
switchgen/core/logging.py
switchgen/core/models.py
switchgen/core/queue.py
switchgen/core/workflows.py
switchgen/resources/fonts/Crimson_Text/CrimsonText-Bold.ttf
switchgen/resources/fonts/Crimson_Text/CrimsonText-BoldItalic.ttf
switchgen/resources/fonts/Crimson_Text/CrimsonText-Italic.ttf
switchgen/resources/fonts/Crimson_Text/CrimsonText-Regular.ttf
switchgen/resources/fonts/Crimson_Text/CrimsonText-SemiBold.ttf
switchgen/resources/fonts/Crimson_Text/CrimsonText-SemiBoldItalic.ttf
switchgen/resources/fonts/Crimson_Text/OFL.txt
switchgen/ui/__init__.py
switchgen/ui/main_window.py
switchgen/ui/model_dialog.py
switchgen/ui/styles/switchsides.css
switchgen/ui/widgets/__init__.py
switchgen-0.1.1.dist-info/METADATA
switchgen-0.1.1.dist-info/WHEEL
switchgen-0.1.1.dist-info/entry_points.txt
switchgen-0.1.1.dist-info/licenses/LICENSE
switchgen-0.1.1.dist-info/RECORD
