Metadata-Version: 2.4
Name: switchgen
Version: 0.1.1
Summary: Image and video generator using ComfyUI as a library
Author: SwitchSides
License-Expression: MIT
License-File: LICENSE
Requires-Python: >=3.10
Requires-Dist: aiohttp>=3.11.8
Requires-Dist: av>=14.2.0
Requires-Dist: einops
Requires-Dist: huggingface-hub>=0.20.0
Requires-Dist: kornia>=0.7.1
Requires-Dist: numpy>=1.25.0
Requires-Dist: pillow>=10.0
Requires-Dist: psutil>=5.9
Requires-Dist: pygobject>=3.42
Requires-Dist: pyyaml
Requires-Dist: safetensors>=0.4.2
Requires-Dist: scipy
Requires-Dist: sentencepiece
Requires-Dist: spandrel
Requires-Dist: tokenizers>=0.13.3
Requires-Dist: torch
Requires-Dist: torchaudio
Requires-Dist: torchsde
Requires-Dist: torchvision
Requires-Dist: tqdm
Requires-Dist: transformers>=4.50.3
Requires-Dist: yarl>=1.18.0
Provides-Extra: dev
Requires-Dist: pytest-asyncio>=0.21; extra == 'dev'
Requires-Dist: pytest>=7.0; extra == 'dev'
